obsidian2quarto/__init__.py
obsidian2quarto/_modidx.py
obsidian2quarto/core.py
obsidian2quarto-0.0.3.dist-info/LICENSE
obsidian2quarto-0.0.3.dist-info/METADATA
obsidian2quarto-0.0.3.dist-info/WHEEL
obsidian2quarto-0.0.3.dist-info/entry_points.txt
obsidian2quarto-0.0.3.dist-info/top_level.txt
obsidian2quarto-0.0.3.dist-info/RECORD
