Metadata-Version: 2.1
Name: obsidian2quarto
Version: 0.0.3
Summary: render obisidian to quarto
Home-page: https://github.com/mone27/https://github.com/44moles/obsidian2quarto
Author: Simone Massaro
Author-email: simone@44moles.com
License: Apache Software License 2.0
Keywords: nbdev jupyter notebook python
Classifier: Development Status :: 4 - Beta
Classifier: Intended Audience :: Developers
Classifier: Natural Language :: English
Classifier: Programming Language :: Python :: 3.7
Classifier: Programming Language :: Python :: 3.8
Classifier: Programming Language :: Python :: 3.9
Classifier: Programming Language :: Python :: 3.10
Classifier: Programming Language :: Python :: 3.11
Classifier: Programming Language :: Python :: 3.12
Classifier: License :: OSI Approved :: Apache Software License
Requires-Python: >=3.7
License-File: LICENSE
Requires-Dist: fastcore
Requires-Dist: pyyaml
Provides-Extra: dev
